compose.py
compose-1.6.1.dist-info/LICENSE
compose-1.6.1.dist-info/METADATA
compose-1.6.1.dist-info/WHEEL
compose-1.6.1.dist-info/top_level.txt
compose-1.6.1.dist-info/RECORD
