Metadata-Version: 2.1
Name: compose
Version: 1.6.1
Summary: The classic ``compose``, with all the Pythonic features.
Home-page: https://github.com/mentalisttraceur/python-compose
Author: Alexander Kozhevnikov
Author-email: mentalisttraceur@gmail.com
License: 0BSD
Classifier: Development Status :: 5 - Production/Stable
Classifier: Programming Language :: Python :: 3
Classifier: Programming Language :: Python :: 2
Classifier: Operating System :: OS Independent
License-File: LICENSE
